eostalk/__init__.py
eostalk/account.py
eostalk/aes.py
eostalk/amount.py
eostalk/block.py
eostalk/blockchain.py
eostalk/blog.py
eostalk/cli.py
eostalk/commit.py
eostalk/converter.py
eostalk/dex.py
eostalk/instance.py
eostalk/post.py
eostalk/profile.py
eostalk/steem.py
eostalk/steemd.py
eostalk/transactionbuilder.py
eostalk/utils.py
eostalk/wallet.py
eostalk/witness.py
eostalk-1.0.2.dist-info/METADATA
eostalk-1.0.2.dist-info/RECORD
eostalk-1.0.2.dist-info/WHEEL
eostalk-1.0.2.dist-info/entry_points.txt
eostalk-1.0.2.dist-info/top_level.txt
eostalkbase/__init__.py
eostalkbase/account.py
eostalkbase/base58.py
eostalkbase/bip38.py
eostalkbase/chains.py
eostalkbase/dictionary.py
eostalkbase/exceptions.py
eostalkbase/http_client.py
eostalkbase/memo.py
eostalkbase/operationids.py
eostalkbase/operations.py
eostalkbase/storage.py
eostalkbase/transactions.py
eostalkbase/types.py
